s3datasets/__init__.py
s3datasets/s3_dataset.py
s3datasets/s3_json_dataset.py
s3datasets/s3_text_dataset.py
tokengenerators/__init__.py
tokengenerators/text_ds_2_tokens_generator.py
typedjson/__init__.py
typedjson/typedjson.py
s3datasets-2.1.1.dist-info/LICENSE
s3datasets-2.1.1.dist-info/METADATA
s3datasets-2.1.1.dist-info/WHEEL
s3datasets-2.1.1.dist-info/top_level.txt
s3datasets-2.1.1.dist-info/RECORD
