Metadata-Version: 2.1
Name: s3datasets
Version: 2.1.1
Summary: Lazy-loading HF Datasets sourced from AWS S3 buckets and a chunking text document tokenizer.
Author-email: Steve Madere <steve@stevemadere.com>
Project-URL: Homepage, https://github.com/stevemadere/s3-datasets
Project-URL: Issues, https://github.com/stevemadere/s3-datasets/issues
Classifier: Programming Language :: Python :: 3
Classifier: License :: OSI Approved :: Apache Software License
Classifier: Operating System :: OS Independent
Classifier: Intended Audience :: Developers
Classifier: Intended Audience :: Education
Classifier: Intended Audience :: Science/Research
Classifier: Topic :: Scientific/Engineering :: Artificial Intelligence
Requires-Python: >=3.6
License-File: LICENSE
Requires-Dist: datasets
Requires-Dist: boto3
Requires-Dist: diskcache
Requires-Dist: transformers
Requires-Dist: torch
Requires-Dist: typing ; python_version < "3.5"
